{"symbols":{"Testing":{"hasNamespace":false,"type":0,"moduleName":"testing","relativePath":"assets\\src\\testing"},"InterFilterParam":{"hasNamespace":false,"type":1,"moduleName":"table-sort","relativePath":"assets\\src\\static\\table-sort"},"InterFilterDropDownParam":{"hasNamespace":false,"type":1,"moduleName":"table-sort","relativePath":"assets\\src\\static\\table-sort"},"InterPagination":{"hasNamespace":false,"type":1,"moduleName":"table-sort","relativePath":"assets\\src\\static\\table-sort"},"InterSortParam":{"hasNamespace":false,"type":1,"moduleName":"table-sort","relativePath":"assets\\src\\static\\table-sort"},"MpSortTable":{"hasNamespace":false,"type":0,"moduleName":"table-sort","relativePath":"assets\\src\\static\\table-sort"},"Store":{"hasNamespace":false,"type":0,"moduleName":"store","relativePath":"assets\\src\\static\\store"},"InitAdminValues":{"hasNamespace":false,"type":1,"moduleName":"store","relativePath":"assets\\src\\static\\store"},"ServerValues":{"hasNamespace":false,"type":1,"moduleName":"server","relativePath":"assets\\src\\static\\server"},"InterSendOnlineFileFormat":{"hasNamespace":false,"type":1,"moduleName":"server","relativePath":"assets\\src\\static\\server"},"InterSendOnline":{"hasNamespace":false,"type":1,"moduleName":"server","relativePath":"assets\\src\\static\\server"},"InterServerResponse":{"hasNamespace":false,"type":1,"moduleName":"server","relativePath":"assets\\src\\static\\server"},"InterFuncBeforeSend":{"hasNamespace":false,"type":1,"moduleName":"server","relativePath":"assets\\src\\static\\server"},"InterFuncProgress":{"hasNamespace":false,"type":1,"moduleName":"server","relativePath":"assets\\src\\static\\server"},"InterFuncSuccess":{"hasNamespace":false,"type":1,"moduleName":"server","relativePath":"assets\\src\\static\\server"},"InterFuncFailure":{"hasNamespace":false,"type":1,"moduleName":"server","relativePath":"assets\\src\\static\\server"},"InterReportHtml":{"hasNamespace":false,"type":1,"moduleName":"server","relativePath":"assets\\src\\static\\server"},"Server":{"hasNamespace":false,"type":0,"moduleName":"server","relativePath":"assets\\src\\static\\server"},"_DeckGroup":{"hasNamespace":false,"type":1,"moduleName":"inter-sp","relativePath":"assets\\src\\interfaces\\inter-sp"},"_Deck":{"hasNamespace":false,"type":1,"moduleName":"inter-sp","relativePath":"assets\\src\\interfaces\\inter-sp"},"_Tag":{"hasNamespace":false,"type":1,"moduleName":"inter-sp","relativePath":"assets\\src\\interfaces\\inter-sp"},"_TimeStamps":{"hasNamespace":false,"type":1,"moduleName":"inter-sp","relativePath":"assets\\src\\interfaces\\inter-sp"},"_Study":{"hasNamespace":false,"type":1,"moduleName":"inter-sp","relativePath":"assets\\src\\interfaces\\inter-sp"},"_Card":{"hasNamespace":false,"type":1,"moduleName":"inter-sp","relativePath":"assets\\src\\interfaces\\inter-sp"},"_CardGroup":{"hasNamespace":false,"type":1,"moduleName":"inter-sp","relativePath":"assets\\src\\interfaces\\inter-sp"},"_ImageItem":{"hasNamespace":false,"type":1,"moduleName":"inter-sp","relativePath":"assets\\src\\interfaces\\inter-sp"},"_ImageBox":{"hasNamespace":false,"type":1,"moduleName":"inter-sp","relativePath":"assets\\src\\interfaces\\inter-sp"},"_Endpoint":{"hasNamespace":false,"type":1,"moduleName":"inter-sbe","relativePath":"assets\\src\\interfaces\\inter-sbe"},"_UserProfile":{"hasNamespace":false,"type":1,"moduleName":"useUserProfile","relativePath":"assets\\src\\composables\\useUserProfile"},"_ProgressChartGraphable":{"hasNamespace":false,"type":1,"moduleName":"useStats","relativePath":"assets\\src\\composables\\useStats"},"_ForecastGraphable":{"hasNamespace":false,"type":1,"moduleName":"useStats","relativePath":"assets\\src\\composables\\useStats"},"_ReviewGraphable":{"hasNamespace":false,"type":1,"moduleName":"useStats","relativePath":"assets\\src\\composables\\useStats"},"_ChartAddedGraphable":{"hasNamespace":false,"type":1,"moduleName":"useStats","relativePath":"assets\\src\\composables\\useStats"},"_ChartAnswerButtons":{"hasNamespace":false,"type":1,"moduleName":"useStats","relativePath":"assets\\src\\composables\\useStats"},"_ChartIntervalGraphable":{"hasNamespace":false,"type":1,"moduleName":"useStats","relativePath":"assets\\src\\composables\\useStats"},"_ChartHourlyBreakdownGraphable":{"hasNamespace":false,"type":1,"moduleName":"useStats","relativePath":"assets\\src\\composables\\useStats"},"_ChartCardTypesGraphable":{"hasNamespace":false,"type":1,"moduleName":"useStats","relativePath":"assets\\src\\composables\\useStats"},"_AdminSettings":{"hasNamespace":false,"type":1,"moduleName":"useSettings","relativePath":"assets\\src\\composables\\useSettings"},"_CDetail":{"hasNamespace":false,"type":1,"moduleName":"RegexHelper","relativePath":"assets\\src\\classes\\RegexHelper"},"RegexHelper":{"hasNamespace":false,"type":0,"moduleName":"RegexHelper","relativePath":"assets\\src\\classes\\RegexHelper"},"ImageHelper":{"hasNamespace":false,"type":0,"moduleName":"ImageHelper","relativePath":"assets\\src\\classes\\ImageHelper"},"_Ajax":{"hasNamespace":false,"type":1,"moduleName":"HandleAjax","relativePath":"assets\\src\\classes\\HandleAjax"},"HandleAjax":{"hasNamespace":false,"type":0,"moduleName":"HandleAjax","relativePath":"assets\\src\\classes\\HandleAjax"},"Common":{"hasNamespace":false,"type":0,"moduleName":"Common","relativePath":"assets\\src\\classes\\Common"},"_CTableDetail":{"hasNamespace":false,"type":1,"moduleName":"TableHelper","relativePath":"assets\\src\\classes\\TableHelper"},"_TableGap":{"hasNamespace":false,"type":1,"moduleName":"TableHelper","relativePath":"assets\\src\\classes\\TableHelper"},"TableHelper":{"hasNamespace":false,"type":0,"moduleName":"TableHelper","relativePath":"assets\\src\\classes\\TableHelper"}},"files":{"assets\\__tests__\\src\\classes\\RegexHelper.spec.ts":"2022-02-28T21:33:28.083Z","assets\\src\\vue-shims.d.ts":"2021-08-07T11:38:31.247Z","assets\\src\\vue-component\\enums.ts":"2021-08-11T00:11:45.704Z","assets\\src\\testing.ts":"2021-08-07T11:38:31.244Z","assets\\src\\static\\table-sort.ts":"2021-08-07T11:38:45.634Z","assets\\src\\static\\store.ts":"2022-02-28T21:33:17.829Z","assets\\src\\static\\server.ts":"2021-09-17T03:47:01.987Z","assets\\src\\shortcodes\\sc-user-dashboard.ts":"2022-02-28T21:33:17.802Z","assets\\src\\interfaces\\inter-sp.ts":"2021-12-15T20:14:14.910Z","assets\\src\\interfaces\\inter-sbe.ts":"2021-10-02T13:15:04.977Z","assets\\src\\composables\\useUserProfile.ts":"2021-12-10T15:03:32.901Z","assets\\src\\composables\\useUserDashboard.ts":"2022-02-28T21:33:17.800Z","assets\\src\\composables\\useTimezones.ts":"2021-12-04T19:17:06.271Z","assets\\src\\composables\\useTagSearch.ts":"2021-12-15T20:11:17.659Z","assets\\src\\composables\\useTags.ts":"2022-03-20T22:14:16.416Z","assets\\src\\composables\\useTableCard.ts":"2021-12-03T14:11:46.739Z","assets\\src\\composables\\useStats.ts":"2021-12-13T14:45:44.216Z","assets\\src\\composables\\useSettings.ts":"2021-12-10T14:35:40.674Z","assets\\src\\composables\\useNewDeckGroup.ts":"2021-11-11T19:46:52.558Z","assets\\src\\composables\\useImageCard.ts":"2022-02-28T21:33:13.378Z","assets\\src\\composables\\useGapCard.ts":"2021-11-16T20:34:31.400Z","assets\\src\\composables\\useDecks.ts":"2021-12-11T18:08:06.134Z","assets\\src\\composables\\useDeckGroupLists.ts":"2022-02-28T21:33:17.798Z","assets\\src\\composables\\useBgImage.ts":"2021-11-30T10:14:35.052Z","assets\\src\\composables\\useBasicCard.ts":"2021-11-16T16:26:30.825Z","assets\\src\\composables\\useAllCards.ts":"2021-12-13T00:43:47.010Z","assets\\src\\classes\\RegexHelper.ts":"2022-04-03T12:48:54.491Z","assets\\src\\classes\\ImageHelper.ts":"2021-12-01T18:34:26.834Z","assets\\src\\classes\\HandleAjax.ts":"2021-11-09T23:22:50.655Z","assets\\src\\classes\\Common.ts":"2021-11-30T20:46:03.357Z","assets\\src\\admin\\install-composition-api.ts":"2021-11-14T12:40:11.299Z","assets\\src\\admin\\admin-tags.ts":"2021-11-11T00:56:03.377Z","assets\\src\\admin\\admin-table-card.ts":"2021-12-10T16:00:51.579Z","assets\\src\\admin\\admin-settings.ts":"2021-12-10T14:25:27.340Z","assets\\src\\admin\\admin-image-card.ts":"2021-11-30T11:04:30.039Z","assets\\src\\admin\\admin-gap-card.ts":"2022-03-20T22:31:45.153Z","assets\\src\\admin\\admin-decks.ts":"2021-12-10T16:00:51.560Z","assets\\src\\admin\\admin-deck-groups.ts":"2021-11-11T21:19:59.697Z","assets\\src\\admin\\admin-basic-card.ts":"2021-12-10T15:59:57.843Z","assets\\src\\admin\\admin-all-cards.ts":"2021-12-01T19:40:29.921Z","assets\\jest.config.ts":"2022-02-28T21:38:37.778Z","assets\\src\\classes\\TableHelper.ts":"2022-04-03T12:46:58.939Z"}}